.flake8
.gitignore
.travis.yml
README.md
README.pypi.rst
dev-requirements.txt
requirements.txt
setup.py
ga4gh/__init__.py
ga4gh/schemas/__init__.py
ga4gh/schemas/_protocol_version.py
ga4gh/schemas/_version.py
ga4gh/schemas/pb.py
ga4gh/schemas/ga4gh/__init__.py
ga4gh/schemas/ga4gh/allele_annotation_service_pb2.py
ga4gh/schemas/ga4gh/allele_annotations_pb2.py
ga4gh/schemas/ga4gh/assay_metadata_pb2.py
ga4gh/schemas/ga4gh/bio_metadata_pb2.py
ga4gh/schemas/ga4gh/bio_metadata_service_pb2.py
ga4gh/schemas/ga4gh/common_pb2.py
ga4gh/schemas/ga4gh/genotype_phenotype_pb2.py
ga4gh/schemas/ga4gh/genotype_phenotype_service_pb2.py
ga4gh/schemas/ga4gh/metadata_pb2.py
ga4gh/schemas/ga4gh/metadata_service_pb2.py
ga4gh/schemas/ga4gh/read_service_pb2.py
ga4gh/schemas/ga4gh/reads_pb2.py
ga4gh/schemas/ga4gh/reference_service_pb2.py
ga4gh/schemas/ga4gh/references_pb2.py
ga4gh/schemas/ga4gh/rna_quantification_pb2.py
ga4gh/schemas/ga4gh/rna_quantification_service_pb2.py
ga4gh/schemas/ga4gh/sequence_annotation_service_pb2.py
ga4gh/schemas/ga4gh/sequence_annotations_pb2.py
ga4gh/schemas/ga4gh/variant_service_pb2.py
ga4gh/schemas/ga4gh/variants_pb2.py
ga4gh/schemas/google/__init__.py
ga4gh/schemas/google/api/__init__.py
ga4gh/schemas/google/api/annotations_pb2.py
ga4gh/schemas/google/api/http_pb2.py
ga4gh_schemas.egg-info/PKG-INFO
ga4gh_schemas.egg-info/SOURCES.txt
ga4gh_schemas.egg-info/dependency_links.txt
ga4gh_schemas.egg-info/namespace_packages.txt
ga4gh_schemas.egg-info/requires.txt
ga4gh_schemas.egg-info/top_level.txt
ga4gh_schemas.egg-info/zip-safe
scripts/process_schemas.py
tests/test_imports.py