Metadata-Version: 1.1
Name: ga4gh-schemas
Version: 0.0.8
Summary: GA4GH api schemas
Home-page: https://github.com/dcolligan/ga4gh-schemas
Author: Global Alliance for Genomics and Health
Author-email: theglobalalliance@genomicsandhealth.org
License: Apache License 2.0
Keywords: genomics,reference
Platform: UNKNOWN
Classifier: Development Status :: 3 - Alpha
Classifier: Intended Audience :: Science/Research
Classifier: License :: OSI Approved :: Apache Software License
Classifier: Natural Language :: English
Classifier: Programming Language :: Python :: 2.7
Classifier: Topic :: Scientific/Engineering :: Bio-Informatics
